ach/__init__.py
ach/constants.py
ach/files/__init__.py
ach/files/file_builder.py
ach/files/file_parser.py
ach/files/file_structure.py
ach/record_types/__init__.py
ach/record_types/addenda.py
ach/record_types/batch_control.py
ach/record_types/batch_header.py
ach/record_types/entry_detail.py
ach/record_types/file_control.py
ach/record_types/file_header.py
ach/record_types/record_fields.py
ach/record_types/record_type_base.py
ach_file-0.1.6b0.dist-info/LICENSE
ach_file-0.1.6b0.dist-info/METADATA
ach_file-0.1.6b0.dist-info/WHEEL
ach_file-0.1.6b0.dist-info/top_level.txt
ach_file-0.1.6b0.dist-info/RECORD
