Metadata-Version: 2.1
Name: ach-file
Version: 0.1.6b0
Summary: Highly configurable and permissive library to generate ACH files
Home-page: https://github.com/freemish/ach-file
Author: Molly Gouletas
Author-email: molly.gouletas@gmail.com
License: MIT License
Classifier: Programming Language :: Python :: 3
Classifier: License :: OSI Approved :: MIT License
Classifier: Operating System :: OS Independent
Requires-Python: >=3.6
License-File: LICENSE
